django_petra/__init__.py
django_petra/celery.py
django_petra/core.py
django_petra/env.py
django_petra/helpers.py
django_petra/managers.py
django_petra/models.py
django_petra/paginate.py
django_petra/paginate_old.py
django_petra/path.py
django_petra/petra_dto.py
django_petra/router.py
django_petra/status.py
django_petra/config/__init__.py
django_petra/config/database.py
django_petra/cors/__init__.py
django_petra/cors/apps.py
django_petra/cors/checks.py
django_petra/cors/conf.py
django_petra/cors/defaults.py
django_petra/cors/middleware.py
django_petra/cors/signals.py
django_petra/filesystem/__init__.py
django_petra/filesystem/storage.py
django_petra/filesystem/the_disks/__init__.py
django_petra/filesystem/the_disks/local.py
django_petra/filesystem/the_disks/s3.py
django_petra/initialize/__init__.py
django_petra/initialize/initialize.py
django_petra/mailer/__init__.py
django_petra/mailer/inline_css.py
django_petra/mailer/send_mail.py
django_petra/mailer/send_mail_queue.py
django_petra/petra_core/__init__.py
django_petra/petra_core/index.py
django_petra/petra_core/permissions.py
django_petra/petra_core/serializers.py
django_petra/project/__init__.py
django_petra/project/apps.py
django_petra/project/models.py
django_petra/project/tasks.py
django_petra/project/urls.py
django_petra/project/views.py
django_petra/project/middleware/APILoggerMiddleware.py
django_petra/project/middleware/__init__.py
django_petra/project/migrations/__init__.py
django_petra/project/utils/__init__.py
django_petra/project/utils/system_environment.py
django_petra/raw_query/__init__.py
django_petra/raw_query/helpers.py
django_petra/raw_query/serializer.py
django_petra/scheduler/__init__.py
django_petra/scheduler/schedule.py
django_petra/scheduler/schedule_cron.py
django_petra-0.0.5.dist-info/LICENSE
django_petra-0.0.5.dist-info/METADATA
django_petra-0.0.5.dist-info/WHEEL
django_petra-0.0.5.dist-info/top_level.txt
django_petra-0.0.5.dist-info/RECORD
