Metadata-Version: 2.1
Name: django-petra
Version: 0.0.5
Summary: A utility package for Django that makes API development easier for developers.
Home-page: https://django-petra.code4mk.org/
Author: Mostafa Kamal
Author-email: hiremostafa@gmail.com
Project-URL: Source, https://github.com/code4mk/django-petra
Project-URL: Changelog, https://github.com/code4mk/django-petra/blob/main/CHANGELOG.md
Keywords: django,drf,django-rest-framework,django-rest-api,django-petra,code4mk
Classifier: Development Status :: 3 - Alpha
Classifier: Intended Audience :: Developers
Classifier: License :: OSI Approved :: MIT License
Classifier: Framework :: Django
Classifier: Framework :: Django :: 3.2
Classifier: Programming Language :: Python :: 3
Classifier: Programming Language :: Python :: 3.6
Classifier: Programming Language :: Python :: 3.7
Classifier: Programming Language :: Python :: 3.8
Classifier: Programming Language :: Python :: 3.9
Classifier: Operating System :: OS Independent
Requires-Python: >=3.6
License-File: LICENSE
Requires-Dist: redis
Requires-Dist: boto3
Requires-Dist: psycopg2-binary
Requires-Dist: djangorestframework
Requires-Dist: python-dotenv
Requires-Dist: celery
Requires-Dist: beautifulsoup4
Requires-Dist: premailer
Requires-Dist: celery-redbeat
